{
  "groups": [
    {
      "name": "slick",
      "type": "com.example.slick.SlickApplicationProperties",
      "sourceType": "com.example.slick.SlickApplicationProperties"
    }
  ],
  "properties": [
    {
      "name": "slick.bar",
      "type": "java.lang.String",
      "sourceType": "com.example.slick.SlickApplicationProperties"
    },
    {
      "name": "slick.foo",
      "type": "java.lang.String",
      "sourceType": "com.example.slick.SlickApplicationProperties"
    }
  ],
  "hints": []
}